pyswip_notebook/__init__.py
pyswip_notebook/_version.py
pyswip_notebook/prolog_notebook.py
pyswip_notebook-0.1.1.dist-info/LICENSE
pyswip_notebook-0.1.1.dist-info/METADATA
pyswip_notebook-0.1.1.dist-info/WHEEL
pyswip_notebook-0.1.1.dist-info/top_level.txt
pyswip_notebook-0.1.1.dist-info/zip-safe
pyswip_notebook-0.1.1.dist-info/RECORD
