Metadata-Version: 2.1
Name: pyswip-notebook
Version: 0.1.1
Summary: Wrapper around the pyswip prolog interpreter to make it useable from within jupyter notebooks.
Home-page: https://github.com/mortacious/pyswip-notebook
Author: Felix Igelbrink
Author-email: felix.igelbrink@uni-osnabrueck.de
License: MIT
Project-URL: Bug Tracker, https://github.com/mortacious/pyswip-notebook/issues
Platform: UNKNOWN
Classifier: Programming Language :: Python :: 3.7
Classifier: Programming Language :: Python :: 3.8
Classifier: Programming Language :: Python :: 3.9
Classifier: Programming Language :: Prolog
Classifier: License :: OSI Approved :: MIT License
Classifier: Operating System :: POSIX :: Linux
Classifier: Operating System :: Microsoft :: Windows
Classifier: Operating System :: MacOS
Classifier: Intended Audience :: Developers
Classifier: Intended Audience :: Science/Research
Classifier: Topic :: Scientific/Engineering
Classifier: Topic :: Software Development
Requires-Python: >=3.6
License-File: LICENSE
Requires-Dist: pyswip
